./.env.example
./.gitignore
./PKG-INFO
./README.md
./agent_display_manager.py
./input_manager.py
./main.py
./mcp.json.example
./mcp_server_manager.py
./pyproject.toml
./session_manager.py
./slash_commands.py
./uv.lock
alpha_vantage_agent-0.1.0.dist-info/METADATA
alpha_vantage_agent-0.1.0.dist-info/WHEEL
alpha_vantage_agent-0.1.0.dist-info/entry_points.txt
alpha_vantage_agent-0.1.0.dist-info/RECORD
