Metadata-Version: 2.4
Name: alpha-vantage-agent
Version: 0.1.0
Summary: OpenAI agents example using Alpha Vantage MCP server
License: MIT
Requires-Python: >=3.13
Requires-Dist: click>=8.2.1
Requires-Dist: json5>=0.12.1
Requires-Dist: loguru>=0.7.3
Requires-Dist: openai
Requires-Dist: openai-agents
Requires-Dist: prompt-toolkit>=3.0.52
Requires-Dist: pydantic
Requires-Dist: python-dotenv
Requires-Dist: rich
